[{"count": 0, "hashtag": "#WIP_2022", "start_time": "2022-09-21T17:46:09.478325", "id": "2022"}, {"count": 0, "hashtag": "#WIP_2016", "start_time": "2022-09-21T17:46:10.622153", "id": "2016"}, {"count": 0, "hashtag": "#WIP_2006", "start_time": "2022-09-21T17:46:11.394497", "id": "2006"}, {"count": 0, "hashtag": "#WIP_2012", "start_time": "2022-09-21T17:46:12.168166", "id": "2012"}, {"count": 0, "hashtag": "#WIP_2026", "start_time": "2022-09-21T17:46:12.935925", "id": "2026"}, {"count": 0, "hashtag": "#WIP_2002", "start_time": "2022-09-21T17:46:13.706403", "id": "2002"}, {"count": 0, "hashtag": "#WIP_2013", "start_time": "2022-09-21T17:46:14.581702", "id": "2013"}, {"count": 0, "hashtag": "#WIP_2027", "start_time": "2022-09-21T17:46:15.342956", "id": "2027"}, {"count": 0, "hashtag": "#WIP_2003", "start_time": "2022-09-21T17:46:16.122280", "id": "2003"}, {"count": 0, "hashtag": "#WIP_2017", "start_time": "2022-09-21T17:46:16.886411", "id": "2017"}, {"count": 0, "hashtag": "#WIP_2007", "start_time": "2022-09-21T17:46:17.649522", "id": "2007"}, {"count": 0, "hashtag": "#WIP_2028", "start_time": "2022-09-21T17:46:18.418063", "id": "2028"}, {"count": 0, "hashtag": "#WIP_1006", "start_time": "2022-09-21T17:46:19.192891", "id": "1006"}, {"count": 0, "hashtag": "#WIP_3002", "start_time": "2022-09-21T17:46:19.959363", "id": "3002"}, {"count": 0, "hashtag": "#WIP_2018", "start_time": "2022-09-21T17:46:20.731595", "id": "2018"}, {"count": 0, "hashtag": "#WIP_1002", "start_time": "2022-09-21T17:46:21.495581", "id": "1002"}, {"count": 0, "hashtag": "#WIP_3006", "start_time": "2022-09-21T17:46:22.270042", "id": "3006"}, {"count": 0, "hashtag": "#WIP_2008", "start_time": "2022-09-21T17:46:23.037265", "id": "2008"}, {"count": 0, "hashtag": "#WIP_2019", "start_time": "2022-09-21T17:46:23.806688", "id": "2019"}, {"count": 0, "hashtag": "#WIP_1003", "start_time": "2022-09-21T17:46:24.572343", "id": "1003"}, {"count": 0, "hashtag": "#WIP_2009", "start_time": "2022-09-21T17:46:25.350543", "id": "2009"}, {"count": 0, "hashtag": "#WIP_3003", "start_time": "2022-09-21T17:46:26.254710", "id": "3003"}, {"count": 0, "hashtag": "#WIP_3004", "start_time": "2022-09-21T17:46:27.030710", "id": "3004"}, {"count": 0, "hashtag": "#WIP_1004", "start_time": "2022-09-21T17:46:27.794332", "id": "1004"}, {"count": 0, "hashtag": "#WIP_1005", "start_time": "2022-09-21T17:46:28.575425", "id": "1005"}, {"count": 1, "hashtag": "#WIP_3001", "start_time": "2022-09-21T17:46:29.390460", "id": "3001"}, {"count": 1, "hashtag": "#WIP_1001", "start_time": "2022-09-21T17:46:30.153748", "id": "1001"}, {"count": 0, "hashtag": "#WIP_3005", "start_time": "2022-09-21T17:46:30.909906", "id": "3005"}, {"count": 0, "hashtag": "#WIP_2010", "start_time": "2022-09-21T17:46:31.668193", "id": "2010"}, {"count": 0, "hashtag": "#WIP_2024", "start_time": "2022-09-21T17:46:32.437363", "id": "2024"}, {"count": 0, "hashtag": "#WIP_2020", "start_time": "2022-09-21T17:46:33.200877", "id": "2020"}, {"count": 0, "hashtag": "#WIP_2014", "start_time": "2022-09-21T17:46:33.969357", "id": "2014"}, {"count": 0, "hashtag": "#WIP_2004", "start_time": "2022-09-21T17:46:34.740924", "id": "2004"}, {"count": 0, "hashtag": "#WIP_2021", "start_time": "2022-09-21T17:46:35.498298", "id": "2021"}, {"count": 0, "hashtag": "#WIP_2005", "start_time": "2022-09-21T17:46:36.264078", "id": "2005"}, {"count": 0, "hashtag": "#WIP_2011", "start_time": "2022-09-21T17:46:37.027646", "id": "2011"}, {"count": 0, "hashtag": "#WIP_2025", "start_time": "2022-09-21T17:46:37.790119", "id": "2025"}, {"count": 0, "hashtag": "#WIP_2001", "start_time": "2022-09-21T17:46:38.556000", "id": "2001"}]